escatastrolib/__about__.py
escatastrolib/__init__.py
escatastrolib/models/Calle.py
escatastrolib/models/InfoCatastral.py
escatastrolib/models/Municipio.py
escatastrolib/models/__init__.py
escatastrolib/utils/__init__.py
escatastrolib/utils/converters.py
escatastrolib/utils/exceptions.py
escatastrolib/utils/statics.py
escatastrolib/utils/utils.py
escatastrolib-0.0.1rc4.dist-info/METADATA
escatastrolib-0.0.1rc4.dist-info/WHEEL
escatastrolib-0.0.1rc4.dist-info/licenses/LICENSE
escatastrolib-0.0.1rc4.dist-info/RECORD
