Metadata-Version: 2.4
Name: ESCatastroLib
Version: 0.0.1rc4
Summary: Una librería de Python para consultar los datos del Catastro COMO OBJETOS. Incluye información geográfica.
Project-URL: Documentation, https://github.com/IvanitiX/ESCatastroLib#readme
Project-URL: Issues, https://github.com/IvanitiX/ESCatastroLib/issues
Project-URL: Source, https://github.com/IvanitiX/ESCatastroLib
Author-email: "Iván V.R" <IvanVR@protonmail.com>
License: Apache License (2.0)
License-File: LICENSE
Keywords: catastro,espana,gis,spain
Classifier: Development Status :: 3 - Alpha
Classifier: Framework :: Pytest
Classifier: Intended Audience :: Developers
Classifier: License :: OSI Approved :: Apache Software License
Classifier: Natural Language :: Spanish
Classifier: Operating System :: OS Independent
Classifier: Programming Language :: Python :: 3
Classifier: Topic :: Software Development :: Build Tools
Requires-Dist: folium
Requires-Dist: geopandas
Requires-Dist: pyarrow
Requires-Dist: pytest
Requires-Dist: requests
Requires-Dist: shapely
Requires-Dist: xmltodict
